scskde/__init__.py
scskde/scskde.py
scskde-0.1.2.dist-info/METADATA
scskde-0.1.2.dist-info/WHEEL
scskde-0.1.2.dist-info/licenses/LICENSE
scskde-0.1.2.dist-info/RECORD
