Metadata-Version: 2.4
Name: scskde
Version: 0.1.2
Summary: Sequential Conditional Sampling from KDEs
Project-URL: Homepage, https://github.com/MutaharChalmers/scskde
Author-email: Mutahar Chalmers <mutahar.chalmers@gmail.com>
License: MIT License
License-File: LICENSE
Classifier: Development Status :: 4 - Beta
Classifier: Intended Audience :: Science/Research
Classifier: License :: OSI Approved :: MIT License
Classifier: Operating System :: OS Independent
Classifier: Programming Language :: Python :: 3
Classifier: Topic :: Scientific/Engineering
Requires-Python: >=3.8
Requires-Dist: kdetools>=0.1.11
Requires-Dist: numpy>=1.18
Requires-Dist: tqdm>=4.66.2
